environmental_override
