Metadata-Version: 1.1
Name: environmental-override
Version: 0.1.2
Summary: Easily configure apps using simple environmental overrides.
Home-page: https://github.com/coddingtonbear/environmental-override
Author: Adam Coddington
Author-email: me@adamcoddington.net
License: UNKNOWN
Platform: UNKNOWN
Classifier: License :: OSI Approved :: MIT License
Classifier: Operating System :: OS Independent
Classifier: Programming Language :: Python :: 3
